LICENSE
README.md
setup.cfg
setup.py
test/__init__.py
test/test_aggregation_histogram_bound.py
test/test_auth_login_request.py
test/test_auth_login_response.py
test/test_auth_login_user.py
test/test_default.py
test/test_document.py
test/test_index.py
test/test_index_analyze_response.py
test/test_index_analyze_response_token.py
test/test_index_index_list_response.py
test/test_meta_aggregation_auto_date_histogram.py
test/test_meta_aggregation_date_histogram.py
test/test_meta_aggregation_date_range.py
test/test_meta_aggregation_histogram.py
test/test_meta_aggregation_ip_range.py
test/test_meta_aggregation_metric.py
test/test_meta_aggregation_range.py
test/test_meta_aggregation_response.py
test/test_meta_aggregations.py
test/test_meta_aggregations_terms.py
test/test_meta_analyzer.py
test/test_meta_bool_query.py
test/test_meta_date_range.py
test/test_meta_exists_query.py
test/test_meta_fuzzy_query.py
test/test_meta_healthz_response.py
test/test_meta_highlight.py
test/test_meta_hit.py
test/test_meta_hits.py
test/test_meta_http_response.py
test/test_meta_http_response_delete_by_query.py
test/test_meta_http_response_document.py
test/test_meta_http_response_error.py
test/test_meta_http_response_id.py
test/test_meta_http_response_index.py
test/test_meta_http_response_record_count.py
test/test_meta_http_response_template.py
test/test_meta_http_retries_response.py
test/test_meta_ids_query.py
test/test_meta_index_analysis.py
test/test_meta_index_settings.py
test/test_meta_index_simple.py
test/test_meta_index_template.py
test/test_meta_ip_range.py
test/test_meta_json_ingest.py
test/test_meta_mappings.py
test/test_meta_match_bool_prefix_query.py
test/test_meta_match_phrase_prefix_query.py
test/test_meta_match_phrase_query.py
test/test_meta_match_query.py
test/test_meta_multi_match_query.py
test/test_meta_page.py
test/test_meta_prefix_query.py
test/test_meta_property.py
test/test_meta_query.py
test/test_meta_query_string_query.py
test/test_meta_range.py
zincsearch_sdk.egg-info/PKG-INFO
zincsearch_sdk.egg-info/SOURCES.txt
zincsearch_sdk.egg-info/dependency_links.txt
zincsearch_sdk.egg-info/requires.txt
zincsearch_sdk.egg-info/top_level.txt
