Metadata-Version: 2.1
Name: zincsearch-sdk
Version: 0.3.3
Summary: Zinc Search engine API
Home-page: https://github.com/zinclabs/sdk-python-zincsearch
Author: Zinc Search
Author-email: team@openapitools.org
License: Apache 2.0
Keywords: OpenAPI,OpenAPI-Generator,Zinc Search engine API
Requires-Python: >=3.6
License-File: LICENSE
